anysqlite3/__init__.py
anysqlite3/py.typed
anysqlite3/version.py
anysqlite3-0.0.1.dist-info/METADATA
anysqlite3-0.0.1.dist-info/WHEEL
anysqlite3-0.0.1.dist-info/licenses/LICENSE.txt
anysqlite3-0.0.1.dist-info/RECORD
