Metadata-Version: 2.4
Name: anysqlite3
Version: 0.0.1
Summary: An async wrapper for the sqlite3 module compatible with both asyncio and trio.
Project-URL: Homepage, https://github.com/merlinz01/anysqlite3
Project-URL: Repository, https://github.com/merlinz01/anysqlite3
Project-URL: Bug Tracker, https://github.com/merlinz01/anysqlite3/issues
Project-URL: Changelog, https://github.com/merlinz01/anysqlite3/blob/master/CHANGELOG.md
License-Expression: MIT
License-File: LICENSE.txt
Requires-Python: >=3.11
Requires-Dist: anyio>=4.7.0
